watchdogCaller/__init__.py
watchdogCaller/main.py
watchdogCaller-0.0.7.dist-info/LICENSE
watchdogCaller-0.0.7.dist-info/METADATA
watchdogCaller-0.0.7.dist-info/WHEEL
watchdogCaller-0.0.7.dist-info/entry_points.txt
watchdogCaller-0.0.7.dist-info/top_level.txt
watchdogCaller-0.0.7.dist-info/RECORD
